Mopidy_Auto-0.5.0.dist-info/METADATA
Mopidy_Auto-0.5.0.dist-info/RECORD
Mopidy_Auto-0.5.0.dist-info/WHEEL
Mopidy_Auto-0.5.0.dist-info/entry_points.txt
Mopidy_Auto-0.5.0.dist-info/top_level.txt
mopidy_auto/__init__.py
mopidy_auto/ext.conf
mopidy_auto/frontend.py
mopidy_auto/web.py
mopidy_auto/static/admin.html
mopidy_auto/static/index.html
mopidy_auto/static/move.html
mopidy_auto/static/css/auto.css
mopidy_auto/static/images/ic_delete_black_48px.svg
mopidy_auto/static/images/ic_fast_forward_black_48px.svg
mopidy_auto/static/images/ic_low_priority_black_48px.svg
mopidy_auto/static/images/ic_pause_black_48px.svg
mopidy_auto/static/images/ic_play_arrow_black_48px.svg
mopidy_auto/static/images/ic_skip_next_black_48px.svg
mopidy_auto/static/images/ic_skip_next_next_black_48px.svg
mopidy_auto/static/js/auto.js
mopidy_auto/static/vendor/grids-responsive-min.css
mopidy_auto/static/vendor/pure-min.css
mopidy_auto/static/vendor/zepto.js
