Metadata-Version: 2.1
Name: Mopidy-Auto
Version: 0.5.0
Summary: Mopidy extension to automate music playback based on time of day
Home-page: https://github.com/gotling/mopidy-auto
Author: Marcus Gotling
Author-email: marcus@gotling.se
License: MIT License
Platform: UNKNOWN
Classifier: Environment :: No Input/Output (Daemon)
Classifier: Intended Audience :: End Users/Desktop
Classifier: License :: OSI Approved :: MIT License
Classifier: Operating System :: OS Independent
Classifier: Programming Language :: Python :: 2
Classifier: Topic :: Multimedia :: Sound/Audio :: Players
Requires-Dist: setuptools
Requires-Dist: Mopidy (>=1.0)
Requires-Dist: Pykka (>=1.1)
